nano_fmm/__init__.py
nano_fmm/__main__.py
nano_fmm/_core.cp310-win_amd64.pyd
nano_fmm/benchmarks.py
nano_fmm/config.cpp
nano_fmm/config.hpp
nano_fmm/converter.py
nano_fmm/flatbush.py
nano_fmm/heap.hpp
nano_fmm/indexer.hpp
nano_fmm/network/match_result.hpp
nano_fmm/network/opath.hpp
nano_fmm/network/projected_point.hpp
nano_fmm/network/ubodt.hpp
nano_fmm/network.cpp
nano_fmm/network.hpp
nano_fmm/osmnx_utils.py
nano_fmm/polyline.hpp
nano_fmm/randoms.hpp
nano_fmm/rapidjson.cpp
nano_fmm/rapidjson_helpers.hpp
nano_fmm/road_network.py
nano_fmm/types.hpp
nano_fmm/utils.hpp
nano_fmm/utils.py
nano_fmm-0.1.3.dist-info/METADATA
nano_fmm-0.1.3.dist-info/WHEEL
nano_fmm-0.1.3.dist-info/entry_points.txt
nano_fmm-0.1.3.dist-info/licenses/LICENSE
nano_fmm-0.1.3.dist-info/RECORD
